README.rst
setup.py
alphabot/__init__.py
alphabot/app.py
alphabot/bot.py
alphabot/engine.py
alphabot.egg-info/PKG-INFO
alphabot.egg-info/SOURCES.txt
alphabot.egg-info/dependency_links.txt
alphabot.egg-info/entry_points.txt
alphabot.egg-info/requires.txt
alphabot.egg-info/top_level.txt
alphabot/scripts/__init__.py
alphabot/scripts/desk.py
alphabot/scripts/random.py