Metadata-Version: 1.1
Name: alphabot
Version: 0.0.0
Summary: Bot that connects to Slack.
Home-page: https://github.com/Nextdoor/alphabot
Author: Mikhail Simin
Author-email: mikhail.simin@gmail.com
License: Apache License, Version 2.0
Keywords: slack,chat,irc,hubot
Platform: UNKNOWN
Classifier: Development Status :: 4 - Beta
Classifier: Topic :: Software Development
Classifier: License :: OSI Approved :: Apache Software License
Classifier: Intended Audience :: Developers
Classifier: Programming Language :: Python
Classifier: Operating System :: POSIX
Classifier: Natural Language :: English
